.gitignore
LICENSE.rst
README.rst
__init__.py
build_docs.sh
publish.sh
pyproject.toml
docs/source/LICENSE.rst
docs/source/README.rst
docs/source/conf.py
docs/source/index.rst
docs/source/modules.rst
docs/source/pytmpdir.Directory.rst
docs/source/pytmpdir.rst
pytmpdir/__init__.py
pytmpdir/dir_setting.py
pytmpdir/directory_.py
pytmpdir/directory_test.py
pytmpdir/disk_file.py
pytmpdir/disk_file_test.py
pytmpdir/file_.py
pytmpdir/memory_file.py
pytmpdir/memory_file_test.py
pytmpdir/named_temp_file_reader.py
pytmpdir/pytmpdir_exception.py
pytmpdir/spooled_named_temporary_file.py
pytmpdir/spooled_named_temporary_file_test.py
pytmpdir.egg-info/PKG-INFO
pytmpdir.egg-info/SOURCES.txt
pytmpdir.egg-info/dependency_links.txt
pytmpdir.egg-info/requires.txt
pytmpdir.egg-info/top_level.txt