Metadata-Version: 2.1
Name: pytmpdir
Version: 1.2.6
Summary: A class representing a file system directory, that deletes on garbage collect.
Author-email: Synerty <support@synerty.com>
Project-URL: Homepage, https://github.com/Synerty/pytmpdir
Project-URL: Download, https://github.com/Synerty/pytmpdir/tarball/1.0.5
Keywords: directory,scan,interrogate,create,open,Python,Synerty
Classifier: Programming Language :: Python :: 3.5
License-File: LICENSE.rst
Requires-Dist: sphinx_rtd_theme
Requires-Dist: sphinx
